[
 {
  "doctype": "Workflow",
  "name": "Shift Assignment Approval",
  "workflow_name": "Shift Assignment Approval",
  "document_type": "Shift Assignment",
  "is_active": 1,
  "override_status": 0,
  "send_email_alert": 0,
  "workflow_state_field": "workflow_state",
  "states": [
   {
    "state": "Draft",
    "doc_status": "0",
    "allow_edit": "HR User"
   },
   {
    "state": "Pending Level 1 Approval",
    "doc_status": "0",
    "allow_edit": "HR Manager"
   },
   {
    "state": "Pending Level 2 Approval",
    "doc_status": "0",
    "allow_edit": "HR Manager"
   },
   {
    "state": "Approved",
    "doc_status": "1",
    "allow_edit": "HR Manager"
   },
   {
    "state": "Rejected",
    "doc_status": "0",
    "allow_edit": "HR User"
   }
  ],
  "transitions": [
   {
    "state": "Draft",
    "action": "Submit for Approval",
    "next_state": "Pending Level 1 Approval",
    "allowed": "HR User",
    "allow_self_approval": 1
   },
   {
    "state": "Pending Level 1 Approval",
    "action": "Level 1 Approve",
    "next_state": "Pending Level 2 Approval",
    "allowed": "All",
    "allow_self_approval": 1
   },
   {
    "state": "Pending Level 1 Approval",
    "action": "Reject",
    "next_state": "Rejected",
    "allowed": "All",
    "allow_self_approval": 1
   },
   {
    "state": "Pending Level 2 Approval",
    "action": "Level 2 Approve",
    "next_state": "Approved",
    "allowed": "All",
    "allow_self_approval": 1
   },
   {
    "state": "Pending Level 2 Approval",
    "action": "Reject",
    "next_state": "Rejected",
    "allowed": "All",
    "allow_self_approval": 1
   },
   {
    "state": "Rejected",
    "action": "Revise",
    "next_state": "Draft",
    "allowed": "HR User",
    "allow_self_approval": 1
   }
  ]
 }
]
