[
 {
  "doctype": "Workflow State",
  "name": "Draft",
  "workflow_state_name": "Draft",
  "style": ""
 },
 {
  "doctype": "Workflow State",
  "name": "Pending Level 1 Approval",
  "workflow_state_name": "Pending Level 1 Approval",
  "style": "Warning"
 },
 {
  "doctype": "Workflow State",
  "name": "Pending Level 2 Approval",
  "workflow_state_name": "Pending Level 2 Approval",
  "style": "Warning"
 },
 {
  "doctype": "Workflow State",
  "name": "Approved",
  "workflow_state_name": "Approved",
  "style": "Success"
 },
 {
  "doctype": "Workflow State",
  "name": "Rejected",
  "workflow_state_name": "Rejected",
  "style": "Danger"
 }
]
